Metadata-Version: 2.1
Name: mmkg-mm-hoi-detection
Version: 0.1.3
Summary: MMKG Models
Home-page: https://gitee.com/pucku/mmkg-mm-hoi-detection
Author: Zhipin Wang
Author-email: zpwang99@foxmail.com
Requires-Python: >=3.7
Requires-Dist: pillow
Requires-Dist: cython
Requires-Dist: pycocotools
Requires-Dist: aiofiles
Requires-Dist: fastapi
Requires-Dist: uvicorn[standard]
Requires-Dist: scipy
Requires-Dist: ftfy
Requires-Dist: regex
Requires-Dist: tqdm
Requires-Dist: opencv-python
